nonebot_plugin_lolinfo/__init__.py
nonebot_plugin_lolinfo/config.py
nonebot_plugin_lolinfo/controllers/__init__.py
nonebot_plugin_lolinfo/controllers/api.py
nonebot_plugin_lolinfo/controllers/ctroll_hinfo.py
nonebot_plugin_lolinfo/controllers/ctroll_rinfo.py
nonebot_plugin_lolinfo/render/__init__.py
nonebot_plugin_lolinfo/render/draw_hinfo.py
nonebot_plugin_lolinfo/render/draw_rinfo.py
nonebot_plugin_lolinfo/templates/css/hinfo.css
nonebot_plugin_lolinfo/templates/css/rinfo.css
nonebot_plugin_lolinfo/templates/hinfo.jinja2
nonebot_plugin_lolinfo/templates/images/_hinfo_notfound.png
nonebot_plugin_lolinfo/templates/images/_rinfo_notfound.png
nonebot_plugin_lolinfo/templates/images/water_print.png
nonebot_plugin_lolinfo/templates/rinfo.jinja2
nonebot_plugin_lolinfo/utils/util_time.py
nonebot_plugin_lolinfo/utils/util_urlpath.py
nonebot_plugin_lolinfo-0.3.3.dist-info/LICENSE
nonebot_plugin_lolinfo-0.3.3.dist-info/METADATA
nonebot_plugin_lolinfo-0.3.3.dist-info/WHEEL
nonebot_plugin_lolinfo-0.3.3.dist-info/RECORD
