Metadata-Version: 2.1
Name: nonebot-plugin-lolinfo
Version: 0.3.3
Summary: 以图片形式将LOL的各种数据发送到QQ中 🎉
License: MIT
Author: Shadow403
Requires-Python: >3.10,<4.0
Classifier: License :: OSI Approved :: MIT License
Classifier: Programming Language :: Python :: 3
Classifier: Programming Language :: Python :: 3.11
Classifier: Programming Language :: Python :: 3.12
Classifier: Programming Language :: Python :: 3.13
Requires-Dist: httpx (>=0.27.0)
Requires-Dist: nonebot-plugin-htmlrender (>=0.3.0)
Requires-Dist: nonebot-plugin-send-anything-anywhere (>=0.7.1,<0.8.0)
Requires-Dist: nonebot2 (>=2.3.0)
